cw_cleaner/__init__.py
cw_cleaner/__main__.py
cw_cleaner-0.1.1.dist-info/entry_points.txt
cw_cleaner-0.1.1.dist-info/WHEEL
cw_cleaner-0.1.1.dist-info/METADATA
cw_cleaner-0.1.1.dist-info/RECORD
